k8sAI/__init__.py
k8sAI/main.py
k8sAI/util.py
k8sAI/kuberag/__init__.py
k8sAI/kuberag/chat.py
k8sAI/kuberag/main.py
k8sAI/kuberag/retriever.py
k8sAI/kuberag/tool_handler.py
k8sAI/kuberag/tools.py
k8sAI/kuberag/embeddings/chroma.sqlite3
k8sAI/kuberag/embeddings/8e153713-b589-4b93-8e0f-cae56950b20d/data_level0.bin
k8sAI/kuberag/embeddings/8e153713-b589-4b93-8e0f-cae56950b20d/header.bin
k8sAI/kuberag/embeddings/8e153713-b589-4b93-8e0f-cae56950b20d/length.bin
k8sAI/kuberag/embeddings/8e153713-b589-4b93-8e0f-cae56950b20d/link_lists.bin
k8sAI/usage/__init__.py
k8sAI/usage/usage.py
k8sAI-0.1.7.dist-info/LICENSE
k8sAI-0.1.7.dist-info/METADATA
k8sAI-0.1.7.dist-info/WHEEL
k8sAI-0.1.7.dist-info/entry_points.txt
k8sAI-0.1.7.dist-info/top_level.txt
k8sAI-0.1.7.dist-info/RECORD
