Metadata-Version: 2.1
Name: k8sAI
Version: 0.1.7
Summary: A conversational AI for Kubernetes users.
Home-page: https://github.com/wilson090/k8sAI
Author: Wilson Spearman
Author-email: wilsonspearman@gmail.com
License-File: LICENSE
Requires-Dist: click
Requires-Dist: langchain
Requires-Dist: langchain-chroma
Requires-Dist: langchain-openai
Requires-Dist: prompt-toolkit
Requires-Dist: rich
Requires-Dist: posthog
